parallax_core/__init__.py
parallax_core/collapse.py
parallax_core/environment.py
parallax_core/evaluator.py
parallax_core/grammar.lark
parallax_core/main.py
parallax_core/nodes.py
parallax_core/parser.py
parallax_core/repl.py
parallax_core/values.py
boron_parallax-1.0.4.dist-info/METADATA
boron_parallax-1.0.4.dist-info/WHEEL
boron_parallax-1.0.4.dist-info/entry_points.txt
boron_parallax-1.0.4.dist-info/top_level.txt
boron_parallax-1.0.4.dist-info/RECORD
