Metadata-Version: 2.4
Name: boron-parallax
Version: 1.0.4
Summary: The World's First Timeline-Oriented Programming Language
Home-page: https://github.com/harsith/parallax
Author: Harsith
Classifier: Development Status :: 4 - Beta
Classifier: Intended Audience :: Developers
Classifier: Topic :: Software Development :: Compilers
Classifier: License :: OSI Approved :: MIT License
Classifier: Programming Language :: Python :: 3
Requires-Python: >=3.10
Requires-Dist: lark
Dynamic: author
Dynamic: classifier
Dynamic: description
Dynamic: description-content-type
Dynamic: home-page
Dynamic: requires-dist
Dynamic: requires-python
Dynamic: summary
